hcpdiff/__init__.py
hcpdiff/train_colo.py
hcpdiff/trainer_ac.py
hcpdiff/trainer_ac_single.py
hcpdiff/trainer_deepspeed.py
hcpdiff/ckpt_manager/__init__.py
hcpdiff/ckpt_manager/ckpt.py
hcpdiff/ckpt_manager/loader.py
hcpdiff/ckpt_manager/format/__init__.py
hcpdiff/ckpt_manager/format/diffusers.py
hcpdiff/ckpt_manager/format/emb.py
hcpdiff/ckpt_manager/format/lora_webui.py
hcpdiff/ckpt_manager/format/sd_single.py
hcpdiff/data/__init__.py
hcpdiff/data/dataset.py
hcpdiff/data/cache/__init__.py
hcpdiff/data/cache/vae.py
hcpdiff/data/handler/__init__.py
hcpdiff/data/handler/controlnet.py
hcpdiff/data/handler/diffusion.py
hcpdiff/data/handler/text.py
hcpdiff/data/source/__init__.py
hcpdiff/data/source/folder_class.py
hcpdiff/data/source/text.py
hcpdiff/data/source/text2img.py
hcpdiff/data/source/text2img_cond.py
hcpdiff/diffusion/__init__.py
hcpdiff/diffusion/noise/__init__.py
hcpdiff/diffusion/noise/pyramid_noise.py
hcpdiff/diffusion/sampler/VP.py
hcpdiff/diffusion/sampler/__init__.py
hcpdiff/diffusion/sampler/base.py
hcpdiff/diffusion/sampler/diffusers.py
hcpdiff/diffusion/sampler/shifter/__init__.py
hcpdiff/diffusion/sampler/shifter/ddpm.py
hcpdiff/diffusion/sampler/shifter/edm.py
hcpdiff/diffusion/sampler/shifter/resolution.py
hcpdiff/diffusion/sampler/sigma_scheduler/__init__.py
hcpdiff/diffusion/sampler/sigma_scheduler/base.py
hcpdiff/diffusion/sampler/sigma_scheduler/ddpm.py
hcpdiff/diffusion/sampler/sigma_scheduler/edm.py
hcpdiff/diffusion/sampler/sigma_scheduler/flow.py
hcpdiff/diffusion/sampler/sigma_scheduler/zero_terminal.py
hcpdiff/diffusion/sampler/solver/__init__.py
hcpdiff/diffusion/sampler/solver/base.py
hcpdiff/diffusion/sampler/solver/euler.py
hcpdiff/diffusion/sampler/timer/__init__.py
hcpdiff/diffusion/sampler/timer/base.py
hcpdiff/easy/__init__.py
hcpdiff/easy/sampler.py
hcpdiff/easy/cfg/__init__.py
hcpdiff/easy/cfg/sd15_train.py
hcpdiff/easy/cfg/sdxl_train.py
hcpdiff/easy/cfg/t2i.py
hcpdiff/easy/model/__init__.py
hcpdiff/easy/model/cnet.py
hcpdiff-2.6.dist-info/licenses/LICENSE
hcpdiff-2.6.dist-info/METADATA
hcpdiff-2.6.dist-info/WHEEL
hcpdiff-2.6.dist-info/entry_points.txt
hcpdiff-2.6.dist-info/top_level.txt
hcpdiff-2.6.dist-info/RECORD
