Metadata-Version: 2.4
Name: hcpdiff
Version: 2.6
Summary: A universal Diffusion toolbox
Home-page: https://github.com/IrisRainbowNeko/HCP-Diffusion
Author: Ziyi Dong
Author-email: rainbow-neko@outlook.com
Classifier: License :: OSI Approved :: Apache Software License
Classifier: Operating System :: OS Independent
Classifier: Programming Language :: Python :: 3
Classifier: Programming Language :: Python :: 3.8
Classifier: Programming Language :: Python :: 3.9
Classifier: Programming Language :: Python :: 3.10
Classifier: Programming Language :: Python :: 3.11
Classifier: Programming Language :: Python :: 3.12
Classifier: Topic :: Scientific/Engineering :: Artificial Intelligence
Requires-Python: >=3.8
License-File: LICENSE
Requires-Dist: rainbowneko>=1.9
Requires-Dist: diffusers
Requires-Dist: matplotlib
Requires-Dist: pyarrow
Requires-Dist: transformers>=4.25.1
Requires-Dist: pytorch-msssim
Requires-Dist: lmdb
Dynamic: author
Dynamic: author-email
Dynamic: classifier
Dynamic: description
Dynamic: description-content-type
Dynamic: home-page
Dynamic: license-file
Dynamic: requires-dist
Dynamic: requires-python
Dynamic: summary
